babylon/__init__.py
babylon-0.0.1.dist-info/LICENSE
babylon-0.0.1.dist-info/METADATA
babylon-0.0.1.dist-info/WHEEL
babylon-0.0.1.dist-info/top_level.txt
babylon-0.0.1.dist-info/RECORD
