Metadata-Version: 2.1
Name: babylon
Version: 0.0.1
Summary: A minimal package to reserve the name babylon
Home-page: https://example.com/babylon
Author: Your Name
Author-email: your.email@example.com
Classifier: Programming Language :: Python :: 3
Classifier: License :: OSI Approved :: MIT License
Classifier: Operating System :: OS Independent
Requires-Python: >=3.6
License-File: LICENSE
